LICENSE
MANIFEST.in
README.md
setup.py
pyctrm/__init__.py
pyctrm.egg-info/PKG-INFO
pyctrm.egg-info/SOURCES.txt
pyctrm.egg-info/dependency_links.txt
pyctrm.egg-info/top_level.txt